README.md
setup.py
ferien/__init__.py
ferien/async_.py
ferien/const.py
ferien/model.py
ferien/sync_.py
ferien/types.py
ferien/util.py
ferien_api.egg-info/PKG-INFO
ferien_api.egg-info/SOURCES.txt
ferien_api.egg-info/dependency_links.txt
ferien_api.egg-info/requires.txt
ferien_api.egg-info/top_level.txt