Metadata-Version: 2.1
Name: ferien-api
Version: 0.3.4
Summary: Python client library for ferien-api.de
Home-page: https://github.com/HazardDede/ferien-api
Author: Dennis Muth
Author-email: den.muth@googlemail.com
License: MIT
Project-URL: Documentation, https://github.com/HazardDede/ferien-api/blob/master/README.mdpp
Project-URL: Source, https://github.com/HazardDede/ferien-api/
Project-URL: Tracker, https://github.com/HazardDede/ferien-api/issues
Keywords: ferien api client
Platform: UNKNOWN
Classifier: Development Status :: 3 - Alpha
Classifier: Intended Audience :: Developers
Classifier: Topic :: Internet :: WWW/HTTP
Classifier: Topic :: Software Development
Classifier: License :: OSI Approved :: MIT License
Classifier: Programming Language :: Python :: 3.5
Classifier: Programming Language :: Python :: 3.6
Classifier: Programming Language :: Python :: 3.7
Requires-Python: >=3.5
